pydesign/__init__.py
pydesign-0.0.1.dist-info/LICENSE
pydesign-0.0.1.dist-info/METADATA
pydesign-0.0.1.dist-info/WHEEL
pydesign-0.0.1.dist-info/top_level.txt
pydesign-0.0.1.dist-info/RECORD
