Metadata-Version: 2.1
Name: pydesign
Version: 0.0.1
Summary: Design Patterns implemented in Python
Home-page: https://github.com/syedjafer/PyDesign
Author: Syed Jafer
Author-email: contact.syedjafer@gmail.com
License: UNKNOWN
Platform: UNKNOWN
Classifier: Programming Language :: Python :: 3
Classifier: License :: OSI Approved :: MIT License
Classifier: Operating System :: OS Independent
Requires-Python: >=3.6
